{"type":"Topology","arcs":[[[1326,3352],[25,-23],[102,-93]],[[1453,3236],[-60,-85],[-42,-60],[-22,-21],[-45,-60],[-20,16],[-7,10],[-2,-5],[-1,-1],[-7,-12],[-15,-22],[-13,-24]],[[1219,2972],[-20,12],[-26,12],[-9,3],[-10,-1],[-23,18],[-17,14]],[[1114,3030],[3,3],[2,7],[17,27],[17,20],[9,14],[3,5],[14,20],[12,19],[6,13],[10,12],[11,15],[3,8],[1,7],[4,8],[4,6],[1,6],[0,8],[2,10],[5,11],[62,72],[26,31]],[[1453,3236],[57,-52],[168,-138],[16,-13],[0,-10]],[[1694,3023],[-39,-18],[-3,-1],[-36,-15],[-36,-17],[-38,-18],[-36,-18],[-8,-5],[-69,-38],[-13,-3]],[[1416,2890],[-5,-1],[-25,0]],[[1386,2889],[-17,3],[-22,5],[-17,5],[-28,17],[-18,12],[-28,18],[-37,23]],[[1084,3047],[17,-14],[11,-8],[2,5]],[[1386,2889],[25,0],[5,1]],[[1694,3023],[-1,-34],[-65,-212],[-165,-94],[-40,2],[-41,18]],[[1382,2703],[-412,183]],[[970,2886],[0,36],[-2,22],[-2,19],[12,2],[59,19],[11,8],[17,25],[8,13],[11,17]],[[858,3315],[2,-12],[2,-22],[4,-29],[1,-8],[0,-7],[4,-10],[10,-10],[9,-15],[6,-6],[9,-6],[15,-8],[15,-9],[24,-10],[0,-1],[15,-7],[18,-4],[6,4],[7,-3],[17,-8],[22,-15],[17,-16],[14,-18],[7,-9],[17,-16],[-2,-4],[-13,-19]],[[970,2886],[-181,79],[50,282]],[[839,3247],[12,66]],[[851,3313],[7,2]],[[858,3315],[170,45],[297,-7],[1,-1]],[[4548,3833],[-1043,-2333],[-87,-98]],[[3418,1402],[-68,104],[-81,84],[-93,62],[-93,44],[-81,80],[-77,79],[-81,98],[-60,84],[-97,44],[-114,17],[-134,53],[-122,62],[-93,66],[-69,98],[-97,62],[-122,52],[-106,17],[-101,-18],[-143,21]],[[1586,2511],[-92,53],[-94,107],[-18,32]],[[1453,3236],[-102,93]],[[1351,3329],[568,91],[2629,413]],[[3418,1402],[-14,-16],[-143,-397],[-38,-392],[-88,-250],[-121,-130],[-257,-179],[-93,-35],[-158,-3],[-170,30],[-146,25],[-69,0],[-83,12],[-67,121],[-41,171],[-22,28]],[[1908,387],[-5,100],[6,143],[17,169],[3,281],[-19,111],[-36,94],[-19,107],[20,196],[14,67],[-15,116],[-32,115],[-19,94],[27,76],[38,80],[10,58],[-43,102],[-65,85],[-81,57],[-76,40],[-47,33]],[[1908,387],[-121,154],[-125,55],[-172,121],[-116,53],[-293,206],[-157,27],[-58,50],[-124,41],[-16,99],[-80,110],[-212,138],[-92,171],[-107,131],[-74,310],[-161,133],[323,286],[170,249],[137,247],[56,255]],[[686,3223],[153,24]],[[898,5162],[93,-3],[93,23],[27,58],[36,6],[55,-64],[119,-32],[75,-100],[133,9],[-12,-80],[11,-21],[45,-2],[30,45],[32,-2],[89,-218],[24,-21],[79,-19],[129,35],[54,56],[28,62],[23,7],[28,126],[177,338],[53,172],[157,300],[20,79],[-27,174],[60,-13],[40,-83],[27,-21],[87,8],[71,-49],[80,-26],[89,-92],[34,-74],[30,-23],[92,-12],[111,-79],[294,-144],[66,-109],[67,-34],[118,7],[97,34],[103,-23],[51,42],[52,14],[69,-130],[106,-22],[35,1],[146,65],[246,-23],[-87,-1459],[-5,-12]],[[1351,3329],[-25,23]],[[851,3313],[-12,-66],[-153,-24]],[[686,3223],[-115,155],[-117,68],[210,186],[91,320],[12,78],[0,138],[-27,208],[-64,166],[-135,198],[-28,75],[111,17],[17,16],[-2,37],[-64,50],[71,143],[38,26],[214,58]],[[3337,5474],[-37,-12],[-3,-37],[30,-31],[31,25],[14,34],[-35,21]],[[1194,3758],[-59,0],[-9,-40],[26,-42],[50,25],[-8,57]]],"transform":{"scale":[0.000026594164494849636,0.00002464121410844177],"translate":[-36.3825226795286,-6.94027698139499]},"objects":{"25SEE250GC_SIR":{"type":"GeometryCollection","geometries":[{"arcs":[[0,1,2,3]],"type":"Polygon","properties":{"ID":34637,"CD_GEOCODI":"250500605000001","TIPO":"URBANO","CD_GEOCODB":"","NM_BAIRRO":"","CD_GEOCODS":"25050060500","NM_SUBDIST":"","CD_GEOCODD":"250500605","NM_DISTRIT":"CUBATI","CD_GEOCODM":"2505006","NM_MUNICIP":"CUBATI","NM_MICRO":"SERIDÓ ORIENTAL PARAIBANO","NM_MESO":"BORBOREMA"}},{"arcs":[[4,5,6,7,-2]],"type":"Polygon","properties":{"ID":34638,"CD_GEOCODI":"250500605000002","TIPO":"URBANO","CD_GEOCODB":"","NM_BAIRRO":"","CD_GEOCODS":"25050060500","NM_SUBDIST":"","CD_GEOCODD":"250500605","NM_DISTRIT":"CUBATI","CD_GEOCODM":"2505006","NM_MUNICIP":"CUBATI","NM_MICRO":"SERIDÓ ORIENTAL PARAIBANO","NM_MESO":"BORBOREMA"}},{"arcs":[[8,-3,-8,9,-6,10,11,12]],"type":"Polygon","properties":{"ID":34639,"CD_GEOCODI":"250500605000003","TIPO":"URBANO","CD_GEOCODB":"","NM_BAIRRO":"","CD_GEOCODS":"25050060500","NM_SUBDIST":"","CD_GEOCODD":"250500605","NM_DISTRIT":"CUBATI","CD_GEOCODM":"2505006","NM_MUNICIP":"CUBATI","NM_MICRO":"SERIDÓ ORIENTAL PARAIBANO","NM_MESO":"BORBOREMA"}},{"arcs":[[13,-13,14,15,16]],"type":"Polygon","properties":{"ID":34640,"CD_GEOCODI":"250500605000004","TIPO":"URBANO","CD_GEOCODB":"","NM_BAIRRO":"","CD_GEOCODS":"25050060500","NM_SUBDIST":"","CD_GEOCODD":"250500605","NM_DISTRIT":"CUBATI","CD_GEOCODM":"2505006","NM_MUNICIP":"CUBATI","NM_MICRO":"SERIDÓ ORIENTAL PARAIBANO","NM_MESO":"BORBOREMA"}},{"arcs":[[17,-4,-9,-14]],"type":"Polygon","properties":{"ID":34641,"CD_GEOCODI":"250500605000005","TIPO":"URBANO","CD_GEOCODB":"","NM_BAIRRO":"","CD_GEOCODS":"25050060500","NM_SUBDIST":"","CD_GEOCODD":"250500605","NM_DISTRIT":"CUBATI","CD_GEOCODM":"2505006","NM_MUNICIP":"CUBATI","NM_MICRO":"SERIDÓ ORIENTAL PARAIBANO","NM_MESO":"BORBOREMA"}},{"arcs":[[18,19,20,-11,-5,21,22]],"type":"Polygon","properties":{"ID":34642,"CD_GEOCODI":"250500605000006","TIPO":"RURAL","CD_GEOCODB":"","NM_BAIRRO":"","CD_GEOCODS":"25050060500","NM_SUBDIST":"","CD_GEOCODD":"250500605","NM_DISTRIT":"CUBATI","CD_GEOCODM":"2505006","NM_MUNICIP":"CUBATI","NM_MICRO":"SERIDÓ ORIENTAL PARAIBANO","NM_MESO":"BORBOREMA"}},{"arcs":[[-20,23,24]],"type":"Polygon","properties":{"ID":34643,"CD_GEOCODI":"250500605000007","TIPO":"RURAL","CD_GEOCODB":"","NM_BAIRRO":"","CD_GEOCODS":"25050060500","NM_SUBDIST":"","CD_GEOCODD":"250500605","NM_DISTRIT":"CUBATI","CD_GEOCODM":"2505006","NM_MUNICIP":"CUBATI","NM_MICRO":"SERIDÓ ORIENTAL PARAIBANO","NM_MESO":"BORBOREMA"}},{"arcs":[[-15,-12,-21,-25,25,26]],"type":"Polygon","properties":{"ID":34644,"CD_GEOCODI":"250500605000008","TIPO":"RURAL","CD_GEOCODB":"","NM_BAIRRO":"","CD_GEOCODS":"25050060500","NM_SUBDIST":"","CD_GEOCODD":"250500605","NM_DISTRIT":"CUBATI","CD_GEOCODM":"2505006","NM_MUNICIP":"CUBATI","NM_MICRO":"SERIDÓ ORIENTAL PARAIBANO","NM_MESO":"BORBOREMA"}},{"arcs":[[27,-23,28,-18,-17,29,30],[31],[32]],"type":"Polygon","properties":{"ID":34645,"CD_GEOCODI":"250500605000009","TIPO":"RURAL","CD_GEOCODB":"","NM_BAIRRO":"","CD_GEOCODS":"25050060500","NM_SUBDIST":"","CD_GEOCODD":"250500605","NM_DISTRIT":"CUBATI","CD_GEOCODM":"2505006","NM_MUNICIP":"CUBATI","NM_MICRO":"SERIDÓ ORIENTAL PARAIBANO","NM_MESO":"BORBOREMA"}},{"arcs":[[-33]],"type":"Polygon","properties":{"ID":34646,"CD_GEOCODI":"250500605000010","TIPO":"RURAL","CD_GEOCODB":"","NM_BAIRRO":"","CD_GEOCODS":"25050060500","NM_SUBDIST":"","CD_GEOCODD":"250500605","NM_DISTRIT":"CUBATI","CD_GEOCODM":"2505006","NM_MUNICIP":"CUBATI","NM_MICRO":"SERIDÓ ORIENTAL PARAIBANO","NM_MESO":"BORBOREMA"}},{"arcs":[[-32]],"type":"Polygon","properties":{"ID":34647,"CD_GEOCODI":"250500605000011","TIPO":"RURAL","CD_GEOCODB":"","NM_BAIRRO":"","CD_GEOCODS":"25050060500","NM_SUBDIST":"","CD_GEOCODD":"250500605","NM_DISTRIT":"CUBATI","CD_GEOCODM":"2505006","NM_MUNICIP":"CUBATI","NM_MICRO":"SERIDÓ ORIENTAL PARAIBANO","NM_MESO":"BORBOREMA"}}]}}}